{
            "regression": "Total",
            "loss": "MSE",
            "nb_parameters": 29140.0,
            "time_elapsed": 646.6218798160553,
            "hparams": {
                        "encoder": [
                                    6,
                                    64,
                                    64,
                                    8
                        ],
                        "decoder": [
                                    8,
                                    64,
                                    64,
                                    4
                        ],
                        "nb_hidden_layers": 3,
                        "size_hidden_layers": 64,
                        "batch_size": 1,
                        "nb_epochs": 400,
                        "lr": 0.003,
                        "max_neighbors": 64,
                        "bn_bool": true,
                        "subsampling": 1600,
                        "r": 0.1
            },
            "train_loss_surf": 0.02872192064921061,
            "train_loss_surf_var": [
                        0.0010321101872250438,
                        0.0006995985750108957,
                        0.040760669857263565,
                        0.07239529490470886
            ],
            "train_loss_vol": 0.012526974413130018,
            "train_loss_vol_var": [
                        0.01129589881747961,
                        0.02190629206597805,
                        0.012358163483440876,
                        0.004547548480331898
            ],
            "val_loss_surf": 0.08854884610045702,
            "val_loss_surf_var": [
                        0.0016532608991838061,
                        0.0007960971823194995,
                        0.22609367719851434,
                        0.12565235225483776
            ],
            "val_loss_vol": 0.05142177806701511,
            "val_loss_vol_var": [
                        0.031126350013073532,
                        0.0777958381222561,
                        0.09116884357936214,
                        0.005596072250045836
            ]
}{
            "regression": "Total",
            "loss": "MSE",
            "nb_parameters": 29140.0,
            "time_elapsed": 649.5823397636414,
            "hparams": {
                        "encoder": [
                                    6,
                                    64,
                                    64,
                                    8
                        ],
                        "decoder": [
                                    8,
                                    64,
                                    64,
                                    4
                        ],
                        "nb_hidden_layers": 3,
                        "size_hidden_layers": 64,
                        "batch_size": 1,
                        "nb_epochs": 400,
                        "lr": 0.003,
                        "max_neighbors": 64,
                        "bn_bool": true,
                        "subsampling": 1600,
                        "r": 0.1
            },
            "train_loss_surf": 0.03358368078867594,
            "train_loss_surf_var": [
                        0.0018100393936038017,
                        0.0009516499703750014,
                        0.05582933500409126,
                        0.07574374228715897
            ],
            "train_loss_vol": 0.013234888182746039,
            "train_loss_vol_var": [
                        0.012816040776669979,
                        0.021843673661351204,
                        0.012837963178753853,
                        0.005441875196993351
            ],
            "val_loss_surf": 0.09566695021931082,
            "val_loss_surf_var": [
                        0.0015989056642865761,
                        0.0009706710858154111,
                        0.25413483671145515,
                        0.12596338060684503
            ],
            "val_loss_vol": 0.05317158931866288,
            "val_loss_vol_var": [
                        0.03246012963354587,
                        0.07621032900642603,
                        0.0969066193967592,
                        0.007109270873479545
            ]
}{
            "regression": "Total",
            "loss": "MSE",
            "nb_parameters": 29140.0,
            "time_elapsed": 649.9780938625336,
            "hparams": {
                        "encoder": [
                                    6,
                                    64,
                                    64,
                                    8
                        ],
                        "decoder": [
                                    8,
                                    64,
                                    64,
                                    4
                        ],
                        "nb_hidden_layers": 3,
                        "size_hidden_layers": 64,
                        "batch_size": 1,
                        "nb_epochs": 400,
                        "lr": 0.003,
                        "max_neighbors": 64,
                        "bn_bool": true,
                        "subsampling": 1600,
                        "r": 0.1
            },
            "train_loss_surf": 0.03256789313422309,
            "train_loss_surf_var": [
                        0.0017988196341320872,
                        0.0006690954905934632,
                        0.05227756127715111,
                        0.0755261480808258
            ],
            "train_loss_vol": 0.012427679697672526,
            "train_loss_vol_var": [
                        0.011623210273683071,
                        0.020777733996510506,
                        0.012246928177773952,
                        0.005062850192189217
            ],
            "val_loss_surf": 0.08668405432254075,
            "val_loss_surf_var": [
                        0.002147928043268621,
                        0.0006265246025577653,
                        0.20983632967108862,
                        0.13412543847225605
            ],
            "val_loss_vol": 0.04656362058594823,
            "val_loss_vol_var": [
                        0.03187819044105709,
                        0.06833428051322699,
                        0.07947608650138135,
                        0.0065659293439239265
            ]
}{
            "regression": "Total",
            "loss": "MSE",
            "nb_parameters": 29140.0,
            "time_elapsed": 646.7310767173767,
            "hparams": {
                        "encoder": [
                                    6,
                                    64,
                                    64,
                                    8
                        ],
                        "decoder": [
                                    8,
                                    64,
                                    64,
                                    4
                        ],
                        "nb_hidden_layers": 3,
                        "size_hidden_layers": 64,
                        "batch_size": 1,
                        "nb_epochs": 400,
                        "lr": 0.003,
                        "max_neighbors": 64,
                        "bn_bool": true,
                        "subsampling": 1600,
                        "r": 0.1
            },
            "train_loss_surf": 0.03487701416015625,
            "train_loss_surf_var": [
                        0.0011015230556949973,
                        0.0006655458128079772,
                        0.06221013143658638,
                        0.07553088665008545
            ],
            "train_loss_vol": 0.012498350938161214,
            "train_loss_vol_var": [
                        0.010843062773346901,
                        0.020770391449332237,
                        0.013066784478724003,
                        0.005313185043632984
            ],
            "val_loss_surf": 0.09270222894847394,
            "val_loss_surf_var": [
                        0.0025181592558510602,
                        0.0012432748637365876,
                        0.2348315337789245,
                        0.13221594654023647
            ],
            "val_loss_vol": 0.044353273953311144,
            "val_loss_vol_var": [
                        0.029695889726281167,
                        0.0702553344075568,
                        0.07110835467465222,
                        0.006353516224771738
            ]
}{
            "regression": "Total",
            "loss": "MSE",
            "nb_parameters": 29140.0,
            "time_elapsed": 651.0161068439484,
            "hparams": {
                        "encoder": [
                                    6,
                                    64,
                                    64,
                                    8
                        ],
                        "decoder": [
                                    8,
                                    64,
                                    64,
                                    4
                        ],
                        "nb_hidden_layers": 3,
                        "size_hidden_layers": 64,
                        "batch_size": 1,
                        "nb_epochs": 400,
                        "lr": 0.003,
                        "max_neighbors": 64,
                        "bn_bool": true,
                        "subsampling": 1600,
                        "r": 0.1
            },
            "train_loss_surf": 0.030726003646850585,
            "train_loss_surf_var": [
                        0.0012239365605637431,
                        0.0005654334672726691,
                        0.047995515167713165,
                        0.07311917096376419
            ],
            "train_loss_vol": 0.012217824988894992,
            "train_loss_vol_var": [
                        0.011013148352503777,
                        0.020503660663962364,
                        0.012300943024456501,
                        0.005053544882684946
            ],
            "val_loss_surf": 0.08924553962424397,
            "val_loss_surf_var": [
                        0.0013818511288263835,
                        0.001432571167970309,
                        0.22089742959942668,
                        0.13327030995860695
            ],
            "val_loss_vol": 0.04759695951361209,
            "val_loss_vol_var": [
                        0.03149415156804025,
                        0.07399610345019028,
                        0.07870922236179467,
                        0.006188356725033373
            ]
}{
            "regression": "Total",
            "loss": "MSE",
            "nb_parameters": 29140.0,
            "time_elapsed": 648.3424777984619,
            "hparams": {
                        "encoder": [
                                    6,
                                    64,
                                    64,
                                    8
                        ],
                        "decoder": [
                                    8,
                                    64,
                                    64,
                                    4
                        ],
                        "nb_hidden_layers": 3,
                        "size_hidden_layers": 64,
                        "batch_size": 1,
                        "nb_epochs": 400,
                        "lr": 0.003,
                        "max_neighbors": 64,
                        "bn_bool": true,
                        "subsampling": 1600,
                        "r": 0.1
            },
            "train_loss_surf": 0.03244987328847249,
            "train_loss_surf_var": [
                        0.001554250018671155,
                        0.00048181318561546504,
                        0.05238842964172363,
                        0.07537499815225601
            ],
            "train_loss_vol": 0.01248864730199178,
            "train_loss_vol_var": [
                        0.011519093997776508,
                        0.020738685503602028,
                        0.012770415283739567,
                        0.004926402121782303
            ],
            "val_loss_surf": 0.10171960680745543,
            "val_loss_surf_var": [
                        0.0016035712556913494,
                        0.0006029645672242622,
                        0.2711932870559394,
                        0.13347859629429876
            ],
            "val_loss_vol": 0.051073643437121063,
            "val_loss_vol_var": [
                        0.02904747591819614,
                        0.06943694035289809,
                        0.09956877122749574,
                        0.006241382483858615
            ]
}{
            "regression": "Total",
            "loss": "MSE",
            "nb_parameters": 29140.0,
            "time_elapsed": 649.0845937728882,
            "hparams": {
                        "encoder": [
                                    6,
                                    64,
                                    64,
                                    8
                        ],
                        "decoder": [
                                    8,
                                    64,
                                    64,
                                    4
                        ],
                        "nb_hidden_layers": 3,
                        "size_hidden_layers": 64,
                        "batch_size": 1,
                        "nb_epochs": 400,
                        "lr": 0.003,
                        "max_neighbors": 64,
                        "bn_bool": true,
                        "subsampling": 1600,
                        "r": 0.1
            },
            "train_loss_surf": 0.03424490557776557,
            "train_loss_surf_var": [
                        0.0014765724772587419,
                        0.0005536432727240026,
                        0.0626789852976799,
                        0.07227049767971039
            ],
            "train_loss_vol": 0.011964715851677788,
            "train_loss_vol_var": [
                        0.010788189247250557,
                        0.02028482034802437,
                        0.011886543594300747,
                        0.004899307619780302
            ],
            "val_loss_surf": 0.07832858323818073,
            "val_loss_surf_var": [
                        0.0026420166235766374,
                        0.0008306113850267138,
                        0.18634712651837618,
                        0.12349457549862564
            ],
            "val_loss_vol": 0.04655327298678458,
            "val_loss_vol_var": [
                        0.03326322388602421,
                        0.07057259087450803,
                        0.0764346672949614,
                        0.005942608951590956
            ]
}{
            "regression": "Total",
            "loss": "MSE",
            "nb_parameters": 29140.0,
            "time_elapsed": 652.7695231437683,
            "hparams": {
                        "encoder": [
                                    6,
                                    64,
                                    64,
                                    8
                        ],
                        "decoder": [
                                    8,
                                    64,
                                    64,
                                    4
                        ],
                        "nb_hidden_layers": 3,
                        "size_hidden_layers": 64,
                        "batch_size": 1,
                        "nb_epochs": 400,
                        "lr": 0.003,
                        "max_neighbors": 64,
                        "bn_bool": true,
                        "subsampling": 1600,
                        "r": 0.1
            },
            "train_loss_surf": 0.03335856861538357,
            "train_loss_surf_var": [
                        0.001446753740310669,
                        0.0003296409558970481,
                        0.05660184845328331,
                        0.0750560387969017
            ],
            "train_loss_vol": 0.012694349553849961,
            "train_loss_vol_var": [
                        0.011815610341727734,
                        0.021314261481165886,
                        0.012274171225726604,
                        0.005373374558985233
            ],
            "val_loss_surf": 0.0905123729025945,
            "val_loss_surf_var": [
                        0.001929805424879305,
                        0.00044077243001083843,
                        0.23241136083379388,
                        0.12726755547337235
            ],
            "val_loss_vol": 0.05316157890483737,
            "val_loss_vol_var": [
                        0.034286439721472564,
                        0.07743458689656109,
                        0.09421900734014343,
                        0.006706278177443892
            ]
}{
            "regression": "Total",
            "loss": "MSE",
            "nb_parameters": 29140.0,
            "time_elapsed": 646.7585961818695,
            "hparams": {
                        "encoder": [
                                    6,
                                    64,
                                    64,
                                    8
                        ],
                        "decoder": [
                                    8,
                                    64,
                                    64,
                                    4
                        ],
                        "nb_hidden_layers": 3,
                        "size_hidden_layers": 64,
                        "batch_size": 1,
                        "nb_epochs": 400,
                        "lr": 0.003,
                        "max_neighbors": 64,
                        "bn_bool": true,
                        "subsampling": 1600,
                        "r": 0.1
            },
            "train_loss_surf": 0.034268585840861,
            "train_loss_surf_var": [
                        0.001693879603408277,
                        0.000738288217689842,
                        0.05928358435630798,
                        0.07535859942436218
            ],
            "train_loss_vol": 0.012371875180138481,
            "train_loss_vol_var": [
                        0.011044458486139774,
                        0.021025996655225754,
                        0.012190209701657295,
                        0.005226857960224152
            ],
            "val_loss_surf": 0.0879028094583191,
            "val_loss_surf_var": [
                        0.0021771478743175974,
                        0.0013781531150016235,
                        0.2118452327209525,
                        0.13621069164946675
            ],
            "val_loss_vol": 0.04584068719996139,
            "val_loss_vol_var": [
                        0.030732815933879463,
                        0.06670625841943548,
                        0.0798987561109243,
                        0.006024915305897593
            ]
}{
            "regression": "Total",
            "loss": "MSE",
            "nb_parameters": 29140.0,
            "time_elapsed": 652.1669676303864,
            "hparams": {
                        "encoder": [
                                    6,
                                    64,
                                    64,
                                    8
                        ],
                        "decoder": [
                                    8,
                                    64,
                                    64,
                                    4
                        ],
                        "nb_hidden_layers": 3,
                        "size_hidden_layers": 64,
                        "batch_size": 1,
                        "nb_epochs": 400,
                        "lr": 0.003,
                        "max_neighbors": 64,
                        "bn_bool": true,
                        "subsampling": 1600,
                        "r": 0.1
            },
            "train_loss_surf": 0.036472037103441025,
            "train_loss_surf_var": [
                        0.000996448565274477,
                        0.0003601529460866004,
                        0.06569920480251312,
                        0.07883231341838837
            ],
            "train_loss_vol": 0.01264286306169298,
            "train_loss_vol_var": [
                        0.012018796056509018,
                        0.020846599712967873,
                        0.012533539906144142,
                        0.005172512494027615
            ],
            "val_loss_surf": 0.09473213617457077,
            "val_loss_surf_var": [
                        0.001214788085053442,
                        0.0004892433600616642,
                        0.2515333478280809,
                        0.12569115636870265
            ],
            "val_loss_vol": 0.053350718296132985,
            "val_loss_vol_var": [
                        0.03283164573367685,
                        0.07829742110334337,
                        0.09592808111628984,
                        0.006345731008332222
            ]
}